wpgtk/__init__.py
wpgtk/__main__.py
wpgtk/data/__init__.py
wpgtk/data/color.py
wpgtk/data/config.py
wpgtk/data/files.py
wpgtk/data/keywords.py
wpgtk/data/reload.py
wpgtk/data/sample.py
wpgtk/data/themer.py
wpgtk/data/util.py
wpgtk/gui/__init__.py
wpgtk/gui/color_grid.py
wpgtk/gui/color_picker.py
wpgtk/gui/keyword_dialog.py
wpgtk/gui/keyword_grid.py
wpgtk/gui/option_grid.py
wpgtk/gui/template_grid.py
wpgtk/gui/theme_picker.py
wpgtk/gui/util.py
wpgtk/misc/.no_sample.sample.png
wpgtk/misc/.nsampler.sample.png
wpgtk/misc/wpg-install.sh
wpgtk/misc/wpg.conf
wpgtk/misc/wpgtk.desktop
wpgtk-6.7.0.dist-info/LICENSE
wpgtk-6.7.0.dist-info/METADATA
wpgtk-6.7.0.dist-info/WHEEL
wpgtk-6.7.0.dist-info/entry_points.txt
wpgtk-6.7.0.dist-info/top_level.txt
wpgtk-6.7.0.dist-info/RECORD
