Metadata-Version: 2.2
Name: wpgtk
Version: 6.7.0
Summary: GTK+ theme/wallpaper manager which uses pywal as its core
Author-email: Fernando Vásquez <fmorataya.04@gmail.com>
License: GPL2
Project-URL: Homepage, https://github.com/deviantfero/wpgtk
Classifier: Environment :: X11 Applications
Classifier: License :: OSI Approved :: GNU General Public License v2 (GPLv2)
Classifier: Operating System :: POSIX :: Linux
Classifier: Programming Language :: Python :: 3.5
Classifier: Programming Language :: Python :: 3.6
Classifier: Programming Language :: Python :: 3.7
Classifier: Programming Language :: Python :: 3.8
Requires-Python: >=3.5
License-File: LICENSE
Requires-Dist: Pillow>=4.2.1
Requires-Dist: pywal>=3.3.0
